[
{"title":"mariadfddfdf","description":"12","urlToImage":"https://phyoekowallpaper.000webhostapp.com/my_wallpaper/126f313.png"},
{"title":"mariadfddfdf","description":"12","urlToImage":"https://phyoekowallpaper.000webhostapp.com/my_wallpaper/126f313.png"},
{"title":"mariadfddfdf","description":"12","urlToImage":"https://phyoekowallpaper.000webhostapp.com/my_wallpaper/126f313.png"},
{"title":"mariadfddfdf","description":"12","urlToImage":"https://phyoekowallpaper.000webhostapp.com/my_wallpaper/126f313.png"},
{"title":"mariadfddfdf","description":"12","urlToImage":"https://phyoekowallpaper.000webhostapp.com/my_wallpaper/126f313.png"}
]